odoo/addons/account_invoice_mass_sending/README.rst
odoo/addons/account_invoice_mass_sending/__init__.py
odoo/addons/account_invoice_mass_sending/__manifest__.py
odoo/addons/account_invoice_mass_sending/i18n/account_invoice_mass_sending.pot
odoo/addons/account_invoice_mass_sending/i18n/es.po
odoo/addons/account_invoice_mass_sending/i18n/fr.po
odoo/addons/account_invoice_mass_sending/models/__init__.py
odoo/addons/account_invoice_mass_sending/models/account_move.py
odoo/addons/account_invoice_mass_sending/readme/CONFIGURE.rst
odoo/addons/account_invoice_mass_sending/readme/CONTRIBUTORS.rst
odoo/addons/account_invoice_mass_sending/readme/DESCRIPTION.rst
odoo/addons/account_invoice_mass_sending/readme/USAGE.rst
odoo/addons/account_invoice_mass_sending/static/description/icon.png
odoo/addons/account_invoice_mass_sending/static/description/index.html
odoo/addons/account_invoice_mass_sending/tests/__init__.py
odoo/addons/account_invoice_mass_sending/tests/test_account_invoice_mass_sending.py
odoo/addons/account_invoice_mass_sending/views/account_invoice_views.xml
odoo/addons/account_invoice_mass_sending/wizards/__init__.py
odoo/addons/account_invoice_mass_sending/wizards/account_invoice_send.py
odoo/addons/account_invoice_mass_sending/wizards/account_invoice_send.xml
odoo14_addon_account_invoice_mass_sending-14.0.2.0.1.dist-info/METADATA
odoo14_addon_account_invoice_mass_sending-14.0.2.0.1.dist-info/WHEEL
odoo14_addon_account_invoice_mass_sending-14.0.2.0.1.dist-info/top_level.txt
odoo14_addon_account_invoice_mass_sending-14.0.2.0.1.dist-info/RECORD
