Metadata-Version: 2.1
Name: odoo14-addon-account_invoice_mass_sending
Version: 14.0.2.0.1
Summary: This addon adds a mass sending feature on invoices.
Home-page: https://github.com/OCA/account-invoicing
Author: ACSONE SA/NV, Odoo Community Association (OCA), Open Net Sàrl
Author-email: support@odoo-community.org
License: AGPL-3
Classifier: Programming Language :: Python
Classifier: Framework :: Odoo
Classifier: Framework :: Odoo :: 14.0
Classifier: License :: OSI Approved :: GNU Affero General Public License v3
Requires-Python: >=3.6
Requires-Dist: odoo14-addon-queue-job
Requires-Dist: odoo<14.1dev,>=14.0a
